es_core_news_sm/__init__.py
es_core_news_sm/meta.json
es_core_news_sm/es_core_news_sm-3.1.0/LICENSE
es_core_news_sm/es_core_news_sm-3.1.0/LICENSES_SOURCES
es_core_news_sm/es_core_news_sm-3.1.0/README.md
es_core_news_sm/es_core_news_sm-3.1.0/accuracy.json
es_core_news_sm/es_core_news_sm-3.1.0/config.cfg
es_core_news_sm/es_core_news_sm-3.1.0/meta.json
es_core_news_sm/es_core_news_sm-3.1.0/tokenizer
es_core_news_sm/es_core_news_sm-3.1.0/attribute_ruler/patterns
es_core_news_sm/es_core_news_sm-3.1.0/lemmatizer/lookups/lookups.bin
es_core_news_sm/es_core_news_sm-3.1.0/morphologizer/cfg
es_core_news_sm/es_core_news_sm-3.1.0/morphologizer/model
es_core_news_sm/es_core_news_sm-3.1.0/ner/cfg
es_core_news_sm/es_core_news_sm-3.1.0/ner/model
es_core_news_sm/es_core_news_sm-3.1.0/ner/moves
es_core_news_sm/es_core_news_sm-3.1.0/parser/cfg
es_core_news_sm/es_core_news_sm-3.1.0/parser/model
es_core_news_sm/es_core_news_sm-3.1.0/parser/moves
es_core_news_sm/es_core_news_sm-3.1.0/senter/cfg
es_core_news_sm/es_core_news_sm-3.1.0/senter/model
es_core_news_sm/es_core_news_sm-3.1.0/tok2vec/cfg
es_core_news_sm/es_core_news_sm-3.1.0/tok2vec/model
es_core_news_sm/es_core_news_sm-3.1.0/vocab/key2row
es_core_news_sm/es_core_news_sm-3.1.0/vocab/lookups.bin
es_core_news_sm/es_core_news_sm-3.1.0/vocab/strings.json
es_core_news_sm/es_core_news_sm-3.1.0/vocab/vectors
es_core_news_sm-3.1.0.dist-info/LICENSE
es_core_news_sm-3.1.0.dist-info/LICENSES_SOURCES
es_core_news_sm-3.1.0.dist-info/METADATA
es_core_news_sm-3.1.0.dist-info/WHEEL
es_core_news_sm-3.1.0.dist-info/entry_points.txt
es_core_news_sm-3.1.0.dist-info/top_level.txt
es_core_news_sm-3.1.0.dist-info/RECORD
