Metadata-Version: 2.1
Name: es_core_news_sm
Version: 3.1.0
Summary: Spanish pipeline optimized for CPU. Components: tok2vec, morphologizer, parser, senter, ner, attribute_ruler, lemmatizer.
Home-page: https://explosion.ai
Author: Explosion
Author-email: contact@explosion.ai
License: GNU GPL 3.0
Platform: UNKNOWN
